[
    {
        "title": "First Lego League Greece",
        "description": "Στο FIRST® LEGO® League Challenge οι ομάδες εμπλέκονται στην έρευνα, την επίλυση προβλημάτων, τον προγραμματισμό και την ρομποτική. Κατασκευάζουν και προγραμματίζουν ένα ρομπότ LEGO® Education SPIKE™ Prime ή LEGO MINDSTORMS® που εκτελεί αποστολές στην θεματική πίστα του Robot Game. Επίσης διενεργούν ένα Project Καινοτομίας στο οποίο προτείνουν λύση σε ένα επιστημονικό πρόβλημα σχετικό με την θεματική της σεζόν.",
        "vetted": true,
        "mapLink": "https://maps.app.goo.gl/fccsYUxyeQFk4TQf9",
        "date": "2024-02-02",
        "organizer": {
            "name": "First Lego League Greece",
            "email": "info@firstlegoleague.gr"
        },
        "participants" : "Karamali Erietta (kaer18687@moraitis.edu.gr), Vitantzakis Dimitris (dvitantzakis@moraitis.edu.gr) Ntinopoulou Stefania (ntst15781@moraitis.edu.gr), Kaloudis Aristomenis (kaar128956@moraitis.edu.gr), Mavrou Christina (mach80576@moraitis.edu.gr), Moschakis Alexandros (moal91690@moraitis.edu.gr), Prapa Marina (prma130481@moraitis.edu.gr), Taka Aliki (taal18596@moraitis.edu.gr)"
    }
]
